verilog/multiplier.v
module half_adder(input a,input b, output s,output c);  
xor sum(s,a,b); 
and carry(c,a,b); 
endmodule

module full_adder(output s, c_out, input a, b, c_in);

wire w1, w2,w3,w4;
xor xor1(w1, a, b);
xor xor2(s, w1, c_in);
and and1(w3, a, b);
and and2(w4, w1, c_in);
or or1(c_out, w3, w4);
endmodule

module bit_adder(input a0 ,a1, a2, a3 ,b0, b1, b2, b3,output s0 ,s1 ,s2 ,s3 ,c);
wire c1,c2,c3;

half_adder h1(a0,b0,s0,c1);
full_adder f1(s1,c2,a1,b1,c1);
full_adder f2(s2,c3,a2,b2,c2);
full_adder f3(s3,c,a3,b3,c3);


endmodule

module main_block(input a0,a1,a2,a3,b,b0,b1,b2,b3,output s0,s1,s2,s3,c);

wire w1,w2,w3,w4;
and a1(w1,a0,b);
and a2(w2,a1,b);
and a3(w3,a2,b);
and a4(w4,a3,b);

bit_adder add1(w1,w2,w3,w4,b0,b1,b2,b3,s0,s1,s2,s3,c);


endmodule

module multiplier(input a0,a1,a2,a3,b0,b1,b2,b3,output p0,p1,p2,p3,p4,p5,p6,p7);

wire w1,w2,w3,w4,w5,w6,w7,w8,w9,w10,w11,w12;
and a1(p0,a0,b0);
and a2(w2,a1,b1);
and a3(w3,a2,b2);
and a4(w4,a3,b3);

main_block m1(a0,a1,a2,a3,b1,w2,w3,w4,1'b0,p1,w5,w6,w7,w8);
main_block m2(a0,a1,a2,a3,b2,w5,w6,w7,w8,p2,w9,w10,w11,w12);
main_block m3(a0,a1,a2,a3,b3,w9,w10,w11,w12,p3,p4,p5,p6,p7);


endmodule

verilog/multiplier_test.v
module test_tb;
reg a0,a1,a2,a3,b0,b1,b2,b3;
wire p0,p1,p2,p3,p4,p5,p6,p7;
integer i;

multiplier test(a0,a1,a2,a3,b0,b1,b2,b3,p0,p1,p2,p3,p4,p5,p6,p7);

initial begin

   $dumpfile("test_tb.vcd");
   $dumpvars(0,test_tb);
   
   for(i=0;i<256;i=i+1)begin
      {a0,a1,a2,a3,b0,b1,b2,b3}=i;
      #10;
   end
    
end

endmodule

verilog/test_tb.vcd
$date
	Mon Nov 28 22:45:51 2022
$end
$version
	Icarus Verilog
$end
$timescale
	1s
$end
$scope module test_tb $end
$var wire 1 ! p7 $end
$var wire 1 " p6 $end
$var wire 1 # p5 $end
$var wire 1 $ p4 $end
$var wire 1 % p3 $end
$var wire 1 & p2 $end
$var wire 1 ' p1 $end
$var wire 1 ( p0 $end
$var reg 1 ) a0 $end
$var reg 1 * a1 $end
$var reg 1 + a2 $end
$var reg 1 , a3 $end
$var reg 1 - b0 $end
$var reg 1 . b1 $end
$var reg 1 / b2 $end
$var reg 1 0 b3 $end
$var integer 32 1 i [31:0] $end
$scope module test $end
$var wire 1 ) a0 $end
$var wire 1 * a1 $end
$var wire 1 + a2 $end
$var wire 1 , a3 $end
$var wire 1 - b0 $end
$var wire 1 . b1 $end
$var wire 1 / b2 $end
$var wire 1 0 b3 $end
$var wire 1 ( p0 $end
$var wire 1 2 w2 $end
$var wire 1 3 w3 $end
$var wire 1 4 w4 $end
$var wire 1 5 w9 $end
$var wire 1 6 w8 $end
$var wire 1 7 w7 $end
$var wire 1 8 w6 $end
$var wire 1 9 w5 $end
$var wire 1 : w12 $end
$var wire 1 ; w11 $end
$var wire 1 < w10 $end
$var wire 1 ! p7 $end
$var wire 1 " p6 $end
$var wire 1 # p5 $end
$var wire 1 $ p4 $end
$var wire 1 % p3 $end
$var wire 1 & p2 $end
$var wire 1 ' p1 $end
$scope module m1 $end
$var wire 1 ) a0 $end
$var wire 1 * a1 $end
$var wire 1 + a2 $end
$var wire 1 , a3 $end
$var wire 1 . b $end
$var wire 1 2 b0 $end
$var wire 1 3 b1 $end
$var wire 1 4 b2 $end
$var wire 1 = b3 $end
$var wire 1 > w1 $end
$var wire 1 ? w2 $end
$var wire 1 @ w3 $end
$var wire 1 A w4 $end
$var wire 1 7 s3 $end
$var wire 1 8 s2 $end
$var wire 1 9 s1 $end
$var wire 1 ' s0 $end
$var wire 1 6 c $end
$scope module add1 $end
$var wire 1 > a0 $end
$var wire 1 ? a1 $end
$var wire 1 @ a2 $end
$var wire 1 A a3 $end
$var wire 1 2 b0 $end
$var wire 1 3 b1 $end
$var wire 1 4 b2 $end
$var wire 1 = b3 $end
$var wire 1 7 s3 $end
$var wire 1 8 s2 $end
$var wire 1 9 s1 $end
$var wire 1 ' s0 $end
$var wire 1 B c3 $end
$var wire 1 C c2 $end
$var wire 1 D c1 $end
$var wire 1 6 c $end
$scope module f1 $end
$var wire 1 ? a $end
$var wire 1 3 b $end
$var wire 1 C c_out $end
$var wire 1 9 s $end
$var wire 1 E w1 $end
$var wire 1 F w3 $end
$var wire 1 G w4 $end
$var wire 1 D c_in $end
$upscope $end
$scope module f2 $end
$var wire 1 @ a $end
$var wire 1 4 b $end
$var wire 1 C c_in $end
$var wire 1 B c_out $end
$var wire 1 8 s $end
$var wire 1 H w1 $end
$var wire 1 I w3 $end
$var wire 1 J w4 $end
$upscope $end
$scope module f3 $end
$var wire 1 A a $end
$var wire 1 = b $end
$var wire 1 B c_in $end
$var wire 1 6 c_out $end
$var wire 1 7 s $end
$var wire 1 K w1 $end
$var wire 1 L w3 $end
$var wire 1 M w4 $end
$upscope $end
$scope module h1 $end
$var wire 1 > a $end
$var wire 1 2 b $end
$var wire 1 D c $end
$var wire 1 ' s $end
$upscope $end
$upscope $end
$upscope $end
$scope module m2 $end
$var wire 1 ) a0 $end
$var wire 1 * a1 $end
$var wire 1 + a2 $end
$var wire 1 , a3 $end
$var wire 1 / b $end
$var wire 1 9 b0 $end
$var wire 1 8 b1 $end
$var wire 1 7 b2 $end
$var wire 1 6 b3 $end
$var wire 1 N w1 $end
$var wire 1 O w2 $end
$var wire 1 P w3 $end
$var wire 1 Q w4 $end
$var wire 1 ; s3 $end
$var wire 1 < s2 $end
$var wire 1 5 s1 $end
$var wire 1 & s0 $end
$var wire 1 : c $end
$scope module add1 $end
$var wire 1 N a0 $end
$var wire 1 O a1 $end
$var wire 1 P a2 $end
$var wire 1 Q a3 $end
$var wire 1 9 b0 $end
$var wire 1 8 b1 $end
$var wire 1 7 b2 $end
$var wire 1 6 b3 $end
$var wire 1 ; s3 $end
$var wire 1 < s2 $end
$var wire 1 5 s1 $end
$var wire 1 & s0 $end
$var wire 1 R c3 $end
$var wire 1 S c2 $end
$var wire 1 T c1 $end
$var wire 1 : c $end
$scope module f1 $end
$var wire 1 O a $end
$var wire 1 8 b $end
$var wire 1 S c_out $end
$var wire 1 5 s $end
$var wire 1 U w1 $end
$var wire 1 V w3 $end
$var wire 1 W w4 $end
$var wire 1 T c_in $end
$upscope $end
$scope module f2 $end
$var wire 1 P a $end
$var wire 1 7 b $end
$var wire 1 S c_in $end
$var wire 1 R c_out $end
$var wire 1 < s $end
$var wire 1 X w1 $end
$var wire 1 Y w3 $end
$var wire 1 Z w4 $end
$upscope $end
$scope module f3 $end
$var wire 1 Q a $end
$var wire 1 6 b $end
$var wire 1 R c_in $end
$var wire 1 : c_out $end
$var wire 1 ; s $end
$var wire 1 [ w1 $end
$var wire 1 \ w3 $end
$var wire 1 ] w4 $end
$upscope $end
$scope module h1 $end
$var wire 1 N a $end
$var wire 1 9 b $end
$var wire 1 T c $end
$var wire 1 & s $end
$upscope $end
$upscope $end
$upscope $end
$scope module m3 $end
$var wire 1 ) a0 $end
$var wire 1 * a1 $end
$var wire 1 + a2 $end
$var wire 1 , a3 $end
$var wire 1 0 b $end
$var wire 1 5 b0 $end
$var wire 1 < b1 $end
$var wire 1 ; b2 $end
$var wire 1 : b3 $end
$var wire 1 ^ w1 $end
$var wire 1 _ w2 $end
$var wire 1 ` w3 $end
$var wire 1 a w4 $end
$var wire 1 " s3 $end
$var wire 1 # s2 $end
$var wire 1 $ s1 $end
$var wire 1 % s0 $end
$var wire 1 ! c $end
$scope module add1 $end
$var wire 1 ^ a0 $end
$var wire 1 _ a1 $end
$var wire 1 ` a2 $end
$var wire 1 a a3 $end
$var wire 1 5 b0 $end
$var wire 1 < b1 $end
$var wire 1 ; b2 $end
$var wire 1 : b3 $end
$var wire 1 " s3 $end
$var wire 1 # s2 $end
$var wire 1 $ s1 $end
$var wire 1 % s0 $end
$var wire 1 b c3 $end
$var wire 1 c c2 $end
$var wire 1 d c1 $end
$var wire 1 ! c $end
$scope module f1 $end
$var wire 1 _ a $end
$var wire 1 < b $end
$var wire 1 c c_out $end
$var wire 1 $ s $end
$var wire 1 e w1 $end
$var wire 1 f w3 $end
$var wire 1 g w4 $end
$var wire 1 d c_in $end
$upscope $end
$scope module f2 $end
$var wire 1 ` a $end
$var wire 1 ; b $end
$var wire 1 c c_in $end
$var wire 1 b c_out $end
$var wire 1 # s $end
$var wire 1 h w1 $end
$var wire 1 i w3 $end
$var wire 1 j w4 $end
$upscope $end
$scope module f3 $end
$var wire 1 a a $end
$var wire 1 : b $end
$var wire 1 b c_in $end
$var wire 1 ! c_out $end
$var wire 1 " s $end
$var wire 1 k w1 $end
$var wire 1 l w3 $end
$var wire 1 m w4 $end
$upscope $end
$scope module h1 $end
$var wire 1 ^ a $end
$var wire 1 5 b $end
$var wire 1 d c $end
$var wire 1 % s $end
$upscope $end
$upscope $end
$upscope $end
$upscope $end
$upscope $end
$enddefinitions $end
#0
$dumpvars
0m
0l
0k
0j
0i
0h
0g
0f
0e
0d
0c
0b
0a
0`
0_
0^
0]
0\
0[
0Z
0Y
0X
0W
0V
0U
0T
0S
0R
0Q
0P
0O
0N
0M
0L
0K
0J
0I
0H
0G
0F
0E
0D
0C
0B
0A
0@
0?
0>
0=
0<
0;
0:
09
08
07
06
05
04
03
02
b0 1
00
0/
0.
0-
0,
0+
0*
0)
0(
0'
0&
0%
0$
0#
0"
0!
$end
#10
10
b1 1
#20
1/
00
b10 1
#30
10
b11 1
#40
1.
0/
00
b100 1
#50
10
b101 1
#60
1/
00
b110 1
#70
10
b111 1
#80
1-
0.
0/
00
b1000 1
#90
10
b1001 1
#100
1/
00
b1010 1
#110
10
b1011 1
#120
1.
0/
00
b1100 1
#130
10
b1101 1
#140
1/
00
b1110 1
#150
10
b1111 1
#160
1,
0-
0.
0/
00
b10000 1
#170
1%
15
1U
18
1"
1H
1k
14
1a
10
b10001 1
#180
0%
1#
05
1h
0U
1;
08
0"
1[
0H
0k
1Q
04
0a
1/
00
b10010 1
#190
1%
15
1U
18
1"
1H
1k
14
1a
10
b10011 1
#200
1$
1e
0%
1<
0#
05
1X
0h
0U
17
0;
08
0"
1K
0[
0H
0k
1A
0Q
04
0a
1.
0/
00
b10100 1
#210
1%
15
1U
18
1"
1H
1k
14
1a
10
b10101 1
#220
0%
1#
05
1h
0U
1;
08
0"
1[
0H
0k
1Q
04
0a
1/
00
b10110 1
#230
1%
15
1U
18
1"
1H
1k
14
1a
10
b10111 1
#240
0$
0e
0%
0<
0#
05
0X
0h
0U
07
0;
08
0"
0K
0[
0H
0k
0A
0Q
04
0a
1-
0.
0/
00
b11000 1
#250
1%
15
1U
18
1"
1H
1k
14
1a
10
b11001 1
#260
0%
1#
05
1h
0U
1;
08
0"
1[
0H
0k
1Q
04
0a
1/
00
b11010 1
#270
1%
15
1U
18
1"
1H
1k
14
1a
10
b11011 1
#280
1$
1e
0%
1<
0#
05
1X
0h
0U
17
0;
08
0"
1K
0[
0H
0k
1A
0Q
04
0a
1.
0/
00
b11100 1
#290
1%
15
1U
18
1"
1H
1k
14
1a
10
b11101 1
#300
0%
1#
05
1h
0U
1;
08
0"
1[
0H
0k
1Q
04
0a
1/
00
b11110 1
#310
1%
15
1U
18
1"
1H
1k
14
1a
10
b11111 1
#320
0$
0e
0%
0<
0#
05
0X
0h
0U
07
0;
08
0"
0K
0[
0H
0k
0A
0Q
04
0a
1+
0,
0-
0.
0/
00
b100000 1
#330
1#
1h
1`
10
b100001 1
#340
1$
1&
1e
19
1<
0#
1E
1X
0h
13
1P
0`
1/
00
b100010 1
#350
1#
1h
1`
10
b100011 1
#360
1%
15
0$
1U
0&
0e
18
09
0<
0#
1H
0E
0X
0h
1@
03
0P
0`
1.
0/
00
b100100 1
#370
1#
1h
1`
10
b100101 1
#380
1$
1&
1e
19
1<
0#
1E
1X
0h
13
1P
0`
1/
00
b100110 1
#390
1#
1h
1`
10
b100111 1
#400
0%
05
0$
0U
0&
0e
08
09
0<
0#
0H
0E
0X
0h
0@
03
0P
0`
1-
0.
0/
00
b101000 1
#410
1#
1h
1`
10
b101001 1
#420
1$
1&
1e
19
1<
0#
1E
1X
0h
13
1P
0`
1/
00
b101010 1
#430
1#
1h
1`
10
b101011 1
#440
1%
15
0$
1U
0&
0e
18
09
0<
0#
1H
0E
0X
0h
1@
03
0P
0`
1.
0/
00
b101100 1
#450
1#
1h
1`
10
b101101 1
#460
1$
1&
1e
19
1<
0#
1E
1X
0h
13
1P
0`
1/
00
b101110 1
#470
1#
1h
1`
10
b101111 1
#480
0%
05
0$
0U
0&
0e
08
09
0<
0#
0H
0E
0X
0h
0@
03
0P
0`
1,
0-
0.
0/
00
b110000 1
#490
1%
15
1U
18
1#
1"
1H
1h
1k
14
1`
1a
10
b110001 1
#500
0%
1$
05
1&
1e
0U
19
1<
1;
08
1#
0"
1E
1X
1[
0H
1h
0k
13
1P
1Q
04
0`
0a
1/
00
b110010 1
#510
1%
15
1!
1U
1m
18
0#
1b
0"
1H
0h
1i
1k
14
1`
1a
10
b110011 1
#520
1$
0&
1e
0!
17
09
1<
0;
0#
0b
0"
0m
1K
0E
1X
0[
0h
0i
0k
1@
1A
03
0P
0Q
04
0`
0a
1.
0/
00
b110100 1
#530
1!
1m
1b
0$
1i
0e
1;
0%
0<
1[
05
0X
16
0U
07
1M
08
1B
0#
0"
0H
1I
0h
1k
14
1`
1a
10
b110101 1
#540
1]
1%
1R
0$
15
1Y
06
1&
0e
1U
17
0M
0!
19
0<
0;
1:
18
0B
0#
0b
1"
0m
1E
0X
1[
0\
1H
0I
0h
0i
1k
13
1P
1Q
04
0`
0a
1/
00
b110110 1
#550
1$
1e
0]
0%
1<
0R
0[
1\
05
1X
0Y
16
0U
07
1M
08
1B
1#
0"
1!
0H
1I
1h
0k
1l
14
1`
1a
10
b110111 1
#560
0$
06
0&
0e
0M
09
0<
0;
0:
0B
0#
0"
0!
0K
0E
0X
0[
0\
0I
0h
0k
0l
0@
0A
03
0P
0Q
04
0`
0a
1-
0.
0/
00
b111000 1
#570
1%
15
1U
18
1#
1"
1H
1h
1k
14
1`
1a
10
b111001 1
#580
0%
1$
05
1&
1e
0U
19
1<
1;
08
1#
0"
1E
1X
1[
0H
1h
0k
13
1P
1Q
04
0`
0a
1/
00
b111010 1
#590
1%
15
1!
1U
1m
18
0#
1b
0"
1H
0h
1i
1k
14
1`
1a
10
b111011 1
#600
1$
0&
1e
0!
17
09
1<
0;
0#
0b
0"
0m
1K
0E
1X
0[
0h
0i
0k
1@
1A
03
0P
0Q
04
0`
0a
1.
0/
00
b111100 1
#610
1!
1m
1b
0$
1i
0e
1;
0%
0<
1[
05
0X
16
0U
07
1M
08
1B
0#
0"
0H
1I
0h
1k
14
1`
1a
10
b111101 1
#620
1]
1%
1R
0$
15
1Y
06
1&
0e
1U
17
0M
0!
19
0<
0;
1:
18
0B
0#
0b
1"
0m
1E
0X
1[
0\
1H
0I
0h
0i
1k
13
1P
1Q
04
0`
0a
1/
00
b111110 1
#630
1$
1e
0]
0%
1<
0R
0[
1\
05
1X
0Y
16
0U
07
1M
08
1B
1#
0"
1!
0H
1I
1h
0k
1l
14
1`
1a
10
b111111 1
#640
0$
06
0&
0e
0M
09
0<
0;
0:
0B
0#
0"
0!
0K
0E
0X
0[
0\
0I
0h
0k
0l
0@
0A
03
0P
0Q
04
0`
0a
1*
0+
0,
0-
0.
0/
00
b1000000 1
#650
1$
1e
1_
10
b1000001 1
#660
1%
15
0$
1U
0e
1O
0_
1/
00
b1000010 1
#670
1$
1e
1_
10
b1000011 1
#680
1&
0%
19
05
0$
1'
1E
0U
0e
12
1?
0O
0_
1.
0/
00
b1000100 1
#690
1$
1e
1_
10
b1000101 1
#700
1%
15
0$
1U
0e
1O
0_
1/
00
b1000110 1
#710
1$
1e
1_
10
b1000111 1
#720
0&
0%
09
05
0$
0'
0E
0U
0e
02
0?
0O
0_
1-
0.
0/
00
b1001000 1
#730
1$
1e
1_
10
b1001001 1
#740
1%
15
0$
1U
0e
1O
0_
1/
00
b1001010 1
#750
1$
1e
1_
10
b1001011 1
#760
1&
0%
19
05
0$
1'
1E
0U
0e
12
1?
0O
0_
1.
0/
00
b1001100 1
#770
1$
1e
1_
10
b1001101 1
#780
1%
15
0$
1U
0e
1O
0_
1/
00
b1001110 1
#790
1$
1e
1_
10
b1001111 1
#800
0&
0%
09
05
0$
0'
0E
0U
0e
02
0?
0O
0_
1,
0-
0.
0/
00
b1010000 1
#810
1%
15
1U
18
1$
1"
1H
1e
1k
14
1_
1a
10
b1010001 1
#820
1#
1%
0<
1h
15
0S
1;
08
0$
0"
1U
0V
1[
0H
0e
0k
1O
1Q
04
0_
0a
1/
00
b1010010 1
#830
1!
1m
1b
0#
1j
1c
1f
0%
1<
05
1S
0U
1V
18
0$
0"
1H
0e
1k
14
1_
1a
10
b1010011 1
#840
0b
1&
1X
0%
1<
0h
0#
0j
0!
19
17
05
0S
0;
08
1$
0c
0"
0m
1'
1E
1K
0U
0V
0[
0H
1e
0f
0k
12
1?
1A
0O
0Q
04
0_
0a
1.
0/
00
b1010100 1
#850
1%
15
1U
1#
18
0$
1c
1"
1H
0e
1f
1k
14
1_
1a
10
b1010101 1
#860
0:
0]
0R
1%
1<
0Z
1h
1#
15
0S
1;
08
1$
0c
0"
1U
0V
1[
0H
1e
0f
0k
1O
1Q
04
0_
0a
1/
00
b1010110 1
#870
1l
0h
1:
0;
1]
1R
1!
0%
0<
1Z
0m
05
1S
0b
0U
1V
0#
0j
18
1$
0c
0"
1H
1e
0f
0k
14
1_
1a
10
b1010111 1
#880
0R
0#
0&
0X
0%
0<
0Z
0h
0:
09
07
05
0S
0;
0]
08
0$
0"
0!
0'
0E
0K
0U
0V
0[
0H
0e
0k
0l
02
0?
0A
0O
0Q
04
0_
0a
1-
0.
0/
00
b1011000 1
#890
1%
15
1U
18
1$
1"
1H
1e
1k
14
1_
1a
10
b1011001 1
#900
1#
1%
0<
1h
15
0S
1;
08
0$
0"
1U
0V
1[
0H
0e
0k
1O
1Q
04
0_
0a
1/
00
b1011010 1
#910
1!
1m
1b
0#
1j
1c
1f
0%
1<
05
1S
0U
1V
18
0$
0"
1H
0e
1k
14
1_
1a
10
b1011011 1
#920
0b
1&
1X
0%
1<
0h
0#
0j
0!
19
17
05
0S
0;
08
1$
0c
0"
0m
1'
1E
1K
0U
0V
0[
0H
1e
0f
0k
12
1?
1A
0O
0Q
04
0_
0a
1.
0/
00
b1011100 1
#930
1%
15
1U
1#
18
0$
1c
1"
1H
0e
1f
1k
14
1_
1a
10
b1011101 1
#940
0:
0]
0R
1%
1<
0Z
1h
1#
15
0S
1;
08
1$
0c
0"
1U
0V
1[
0H
1e
0f
0k
1O
1Q
04
0_
0a
1/
00
b1011110 1
#950
1l
0h
1:
0;
1]
1R
1!
0%
0<
1Z
0m
05
1S
0b
0U
1V
0#
0j
18
1$
0c
0"
1H
1e
0f
0k
14
1_
1a
10
b1011111 1
#960
0R
0#
0&
0X
0%
0<
0Z
0h
0:
09
07
05
0S
0;
0]
08
0$
0"
0!
0'
0E
0K
0U
0V
0[
0H
0e
0k
0l
02
0?
0A
0O
0Q
04
0_
0a
1+
0,
0-
0.
0/
00
b1100000 1
#970
1$
1#
1e
1h
1_
1`
10
b1100001 1
#980
1&
1%
19
15
1<
1$
0#
1E
1U
1X
1e
0h
13
1O
1P
0_
0`
1/
00
b1100010 1
#990
1"
1b
1j
0$
1c
0#
0e
1f
1h
1_
1`
10
b1100011 1
#1000
0"
1%
0b
18
15
0<
0$
0c
0#
0j
1'
1H
1U
0X
0e
0f
0h
12
1?
1@
03
0O
0P
0_
0`
1.
0/
00
b1100100 1
#1010
1$
1#
1e
1h
1_
1`
10
b1100101 1
#1020
1Y
17
1;
1B
1R
0&
08
1J
1%
0Z
09
1C
15
0S
0<
0$
1#
0E
1F
1U
0V
0X
0e
1h
13
1O
1P
0_
0`
1/
00
b1100110 1
#1030
1"
1$
0#
1b
1e
0h
1i
1_
1`
10
b1100111 1
#1040
07
0B
0%
0;
0"
0J
0C
05
0<
0R
0$
0#
0b
0'
0H
0F
0U
0X
0Y
0e
0h
0i
02
0?
0@
03
0O
0P
0_
0`
1-
0.
0/
00
b1101000 1
#1050
1$
1#
1e
1h
1_
1`
10
b1101001 1
#1060
1&
1%
19
15
1<
1$
0#
1E
1U
1X
1e
0h
13
1O
1P
0_
0`
1/
00
b1101010 1
#1070
1"
1b
1j
0$
1c
0#
0e
1f
1h
1_
1`
10
b1101011 1
#1080
0"
1%
0b
18
15
0<
0$
0c
0#
0j
1'
1H
1U
0X
0e
0f
0h
12
1?
1@
03
0O
0P
0_
0`
1.
0/
00
b1101100 1
#1090
1$
1#
1e
1h
1_
1`
10
b1101101 1
#1100
1Y
17
1;
1B
1R
0&
08
1J
1%
0Z
09
1C
15
0S
0<
0$
1#
0E
1F
1U
0V
0X
0e
1h
13
1O
1P
0_
0`
1/
00
b1101110 1
#1110
1"
1$
0#
1b
1e
0h
1i
1_
1`
10
b1101111 1
#1120
07
0B
0%
0;
0"
0J
0C
05
0<
0R
0$
0#
0b
0'
0H
0F
0U
0X
0Y
0e
0h
0i
02
0?
0@
03
0O
0P
0_
0`
1,
0-
0.
0/
00
b1110000 1
#1130
1%
15
1U
18
1$
1#
1"
1H
1e
1h
1k
14
1_
1`
1a
10
b1110001 1
#1140
0:
0]
0R
1&
1%
0Z
19
15
0S
1<
1;
08
1$
1#
0"
1E
1U
0V
1X
1[
0H
1e
1h
0k
13
1O
1P
1Q
04
0_
0`
0a
1/
00
b1110010 1
#1150
1l
1:
0;
1]
1R
0%
0<
1Z
05
1S
1!
0U
1V
0m
18
1$
0c
1#
0b
0"
1H
1e
0f
1h
0i
0k
14
1_
1`
1a
10
b1110011 1
#1160
1%
0R
0:
17
15
0S
1<
0Z
0;
0]
1$
0#
0"
0!
1'
1K
1U
0V
1X
0[
1e
0h
0k
0l
12
1?
1@
1A
03
0O
0P
0Q
04
0_
0`
0a
1.
0/
00
b1110100 1
#1170
1i
1;
1!
0%
0<
1[
1m
05
0X
16
1b
0U
07
1M
0j
08
1B
1$
0c
0#
0"
0H
1I
1e
0f
0h
1k
14
1_
1`
1a
10
b1110101 1
#1180
0]
0R
0S
0Y
16
0&
1J
1%
0V
07
1M
0!
09
1C
15
1<
0;
1:
08
1B
1$
0#
0b
1"
0m
0E
1F
1U
1X
0[
1\
1H
0I
1e
0h
0i
1k
13
1O
1P
1Q
04
0_
0`
0a
1/
00
b1110110 1
#1190
1i
1;
1R
0%
0<
1Z
05
1S
1b
0U
1V
0j
18
0J
1$
0c
0#
1"
1!
0H
1I
1e
0f
0h
0k
1l
14
1_
1`
1a
10
b1110111 1
#1200
06
08
0%
0R
0M
0C
05
0S
0<
0Z
0;
0]
0:
0B
0$
0#
0b
0"
0m
0!
0'
0K
0F
0U
0V
0X
0[
0\
0I
0e
0h
0i
0k
0l
02
0?
0@
0A
03
0O
0P
0Q
04
0_
0`
0a
1-
0.
0/
00
b1111000 1
#1210
1%
15
1U
18
1$
1#
1"
1H
1e
1h
1k
14
1_
1`
1a
10
b1111001 1
#1220
0:
0]
0R
1&
1%
0Z
19
15
0S
1<
1;
08
1$
1#
0"
1E
1U
0V
1X
1[
0H
1e
1h
0k
13
1O
1P
1Q
04
0_
0`
0a
1/
00
b1111010 1
#1230
1l
1:
0;
1]
1R
0%
0<
1Z
05
1S
1!
0U
1V
0m
18
1$
0c
1#
0b
0"
1H
1e
0f
1h
0i
0k
14
1_
1`
1a
10
b1111011 1
#1240
1%
0R
0:
17
15
0S
1<
0Z
0;
0]
1$
0#
0"
0!
1'
1K
1U
0V
1X
0[
1e
0h
0k
0l
12
1?
1@
1A
03
0O
0P
0Q
04
0_
0`
0a
1.
0/
00
b1111100 1
#1250
1i
1;
1!
0%
0<
1[
1m
05
0X
16
1b
0U
07
1M
0j
08
1B
1$
0c
0#
0"
0H
1I
1e
0f
0h
1k
14
1_
1`
1a
10
b1111101 1
#1260
0]
0R
0S
0Y
16
0&
1J
1%
0V
07
1M
0!
09
1C
15
1<
0;
1:
08
1B
1$
0#
0b
1"
0m
0E
1F
1U
1X
0[
1\
1H
0I
1e
0h
0i
1k
13
1O
1P
1Q
04
0_
0`
0a
1/
00
b1111110 1
#1270
1i
1;
1R
0%
0<
1Z
05
1S
1b
0U
1V
0j
18
0J
1$
0c
0#
1"
1!
0H
1I
1e
0f
0h
0k
1l
14
1_
1`
1a
10
b1111111 1
#1280
06
08
0%
0R
0M
0C
05
0S
0<
0Z
0;
0]
0:
0B
0$
0#
0b
0"
0m
0!
0'
0K
0F
0U
0V
0X
0[
0\
0I
0e
0h
0i
0k
0l
02
0?
0@
0A
03
0O
0P
0Q
04
0_
0`
0a
1)
0*
0+
0,
0-
0.
0/
00
b10000000 1
#1290
1%
1^
10
b10000001 1
#1300
1&
0%
1N
0^
1/
00
b10000010 1
#1310
1%
1^
10
b10000011 1
#1320
1'
0&
0%
1>
0N
0^
1.
0/
00
b10000100 1
#1330
1%
1^
10
b10000101 1
#1340
1&
0%
1N
0^
1/
00
b10000110 1
#1350
1%
1^
10
b10000111 1
#1360
0'
0&
0%
1(
0>
0N
0^
1-
0.
0/
00
b10001000 1
#1370
1%
1^
10
b10001001 1
#1380
1&
0%
1N
0^
1/
00
b10001010 1
#1390
1%
1^
10
b10001011 1
#1400
1'
0&
0%
1>
0N
0^
1.
0/
00
b10001100 1
#1410
1%
1^
10
b10001101 1
#1420
1&
0%
1N
0^
1/
00
b10001110 1
#1430
1%
1^
10
b10001111 1
#1440
0'
0&
0%
0(
0>
0N
0^
1,
0-
0.
0/
00
b10010000 1
#1450
1$
1d
15
1U
18
1"
1H
0%
1k
14
1^
1a
10
b10010001 1
#1460
1#
05
1h
0U
1;
08
0$
0"
1&
1[
0H
0%
0d
0k
1N
1Q
04
0^
0a
1/
00
b10010010 1
#1470
1$
1d
15
1U
18
1"
1H
0%
1k
14
1^
1a
10
b10010011 1
#1480
1e
1<
0#
05
1X
0h
0U
17
0;
08
1$
0"
1'
1K
0&
0[
0H
0%
0d
0k
1>
1A
0N
0Q
04
0^
0a
1.
0/
00
b10010100 1
#1490
1#
1c
1g
0$
1d
15
1U
18
1"
1H
0%
1k
14
1^
1a
10
b10010101 1
#1500
05
1h
0U
0c
1;
08
0g
1$
0"
1&
1[
0H
0%
0d
0k
1N
1Q
04
0^
0a
1/
00
b10010110 1
#1510
1!
1m
1b
0#
1j
1c
1g
0$
1d
15
1U
18
0"
1H
0%
1k
14
1^
1a
10
b10010111 1
#1520
0e
0b
0<
05
0j
0X
0h
0U
0c
0!
07
0;
08
0g
0$
0"
0m
0'
0K
0&
0[
0H
0%
0d
0k
1(
0>
0A
0N
0Q
04
0^
0a
1-
0.
0/
00
b10011000 1
#1530
1$
1d
15
1U
18
1"
1H
0%
1k
14
1^
1a
10
b10011001 1
#1540
1#
05
1h
0U
1;
08
0$
0"
1&
1[
0H
0%
0d
0k
1N
1Q
04
0^
0a
1/
00
b10011010 1
#1550
1$
1d
15
1U
18
1"
1H
0%
1k
14
1^
1a
10
b10011011 1
#1560
1e
1<
0#
05
1X
0h
0U
17
0;
08
1$
0"
1'
1K
0&
0[
0H
0%
0d
0k
1>
1A
0N
0Q
04
0^
0a
1.
0/
00
b10011100 1
#1570
1#
1c
1g
0$
1d
15
1U
18
1"
1H
0%
1k
14
1^
1a
10
b10011101 1
#1580
05
1h
0U
0c
1;
08
0g
1$
0"
1&
1[
0H
0%
0d
0k
1N
1Q
04
0^
0a
1/
00
b10011110 1
#1590
1!
1m
1b
0#
1j
1c
1g
0$
1d
15
1U
18
0"
1H
0%
1k
14
1^
1a
10
b10011111 1
#1600
0e
0b
0<
05
0j
0X
0h
0U
0c
0!
07
0;
08
0g
0$
0"
0m
0'
0K
0&
0[
0H
0%
0d
0k
0(
0>
0A
0N
0Q
04
0^
0a
1+
0,
0-
0.
0/
00
b10100000 1
#1610
1#
1%
1h
1^
1`
10
b10100001 1
#1620
15
1$
1T
1e
19
1<
0#
1E
0&
1X
1%
0h
13
1N
1P
0^
0`
1/
00
b10100010 1
#1630
1"
1b
1j
1c
1g
0$
0#
0%
1d
1h
1^
1`
10
b10100011 1
#1640
0"
1U
0e
0c
0b
18
09
15
0<
0g
0$
0#
0j
1'
1H
0E
0&
0T
0X
1%
0d
0h
1>
1@
03
0N
0P
0^
0`
1.
0/
00
b10100100 1
#1650
1$
1#
0%
1d
1h
1^
1`
10
b10100101 1
#1660
1;
1R
1Z
1S
1W
05
1T
0e
19
0<
0$
1#
1E
0&
1X
0%
0d
1h
13
1N
1P
0^
0`
1/
00
b10100110 1
#1670
1"
0#
1b
1%
0h
1i
1^
1`
10
b10100111 1
#1680
0$
0;
0U
0S
0e
0R
0"
08
09
0W
05
0<
0Z
0#
0b
0'
0H
0E
0&
0T
0X
0%
0h
0i
1(
0>
0@
03
0N
0P
0^
0`
1-
0.
0/
00
b10101000 1
#1690
1#
1%
1h
1^
1`
10
b10101001 1
#1700
15
1$
1T
1e
19
1<
0#
1E
0&
1X
1%
0h
13
1N
1P
0^
0`
1/
00
b10101010 1
#1710
1"
1b
1j
1c
1g
0$
0#
0%
1d
1h
1^
1`
10
b10101011 1
